pywaveapps
