Metadata-Version: 2.1
Name: PyWaveApps
Version: 1.1.1
Summary: API Connection to the WaveApps (https://www.waveapps.com/) API.
Home-page: https://github.com/The-Nicholas-R-Barrow-Company-LLC/PyWaveApps
Author: The Nicholas R. Barrow Company, LLC
Author-email: me@nicholasrbarrow.com
License: MIT
Project-URL: Source, https://github.com/The-Nicholas-R-Barrow-Company-LLC/PyWaveApps
Project-URL: Tracker, https://github.com/The-Nicholas-R-Barrow-Company-LLC/PyWaveApps/issues
Platform: UNKNOWN
Classifier: License :: OSI Approved :: MIT License
Classifier: Programming Language :: Python :: 3
Classifier: Programming Language :: Python :: 3.9
Classifier: Programming Language :: Python :: 3.10
License-File: LICENSE
